snakemake/__init__.py
snakemake/__main__.py
snakemake/_version.py
snakemake/api.py
snakemake/benchmark.py
snakemake/checkpoints.py
snakemake/cli.py
snakemake/cwl.py
snakemake/dag.py
snakemake/decorators.py
snakemake/exceptions.py
snakemake/gui.html
snakemake/gui.py
snakemake/ioflags.py
snakemake/jobs.py
snakemake/logging.py
snakemake/modules.py
snakemake/notebook.py
snakemake/output_index.py
snakemake/parser.py
snakemake/path_modifier.py
snakemake/pathvars.py
snakemake/persistence.py
snakemake/profiles.py
snakemake/report.css
snakemake/resources.py
snakemake/ruleinfo.py
snakemake/rules.py
snakemake/shell.py
snakemake/sourcecache.py
snakemake/spawn_jobs.py
snakemake/storage.py
snakemake/target_jobs.py
snakemake/utils.py
snakemake/workflow.py
snakemake/wrapper.py
snakemake/assets/__init__.py
snakemake/assets/data/@types-clone/LICENSE
snakemake/assets/data/@types-estree/LICENSE
snakemake/assets/data/array-flat-polyfill/LICENSE
snakemake/assets/data/clone/LICENSE
snakemake/assets/data/commons-math/LICENSE.txt
snakemake/assets/data/commons-math/NOTICE.txt
snakemake/assets/data/d3-array/LICENSE
snakemake/assets/data/d3-color/LICENSE
snakemake/assets/data/d3-contour/LICENSE
snakemake/assets/data/d3-delaunay/LICENSE
snakemake/assets/data/d3-dispatch/LICENSE
snakemake/assets/data/d3-dsv/LICENSE
snakemake/assets/data/d3-force/LICENSE
snakemake/assets/data/d3-format/LICENSE
snakemake/assets/data/d3-geo/LICENSE
snakemake/assets/data/d3-geo-projection/LICENSE
snakemake/assets/data/d3-hierarchy/LICENSE
snakemake/assets/data/d3-interpolate/LICENSE
snakemake/assets/data/d3-path/LICENSE
snakemake/assets/data/d3-quadtree/LICENSE
snakemake/assets/data/d3-regression/LICENSE
snakemake/assets/data/d3-scale/LICENSE
snakemake/assets/data/d3-shape/LICENSE
snakemake/assets/data/d3-time/LICENSE
snakemake/assets/data/d3-time-format/LICENSE
snakemake/assets/data/d3-timer/LICENSE
snakemake/assets/data/delaunator/LICENSE
snakemake/assets/data/esprima/LICENSE.BSD
snakemake-9.16.2.dist-info/licenses/LICENSE.md
snakemake-9.16.2.dist-info/METADATA
snakemake-9.16.2.dist-info/WHEEL
snakemake-9.16.2.dist-info/entry_points.txt
snakemake-9.16.2.dist-info/top_level.txt
snakemake-9.16.2.dist-info/RECORD
